hakku/__init__.py
hakku/__main__.py
hakku/analysis.py
hakku/article.py
hakku/synonyms.py
hakku/viridis.npy
hakku/visualization.py
hakku/word_occurrance.py
hakku-0.1.3.dist-info/DESCRIPTION.rst
hakku-0.1.3.dist-info/METADATA
hakku-0.1.3.dist-info/RECORD
hakku-0.1.3.dist-info/WHEEL
hakku-0.1.3.dist-info/metadata.json
hakku-0.1.3.dist-info/top_level.txt
