Metadata-Version: 2.0
Name: hakku
Version: 0.1.3
Summary: Tool for article clustering based on word counts in titles and keywords.
Home-page: UNKNOWN
Author: Ilkka Pölönen, Tuomo Sipola, Paavo Nieminen, Jarno Kiesiläinen
Author-email: UNKNOWN
License: MIT
Platform: UNKNOWN
Requires-Python: >=3, <4
Requires-Dist: PyQt5
Requires-Dist: ete3
Requires-Dist: nltk
Requires-Dist: numpy
Requires-Dist: scipy
